Workbook

Sheet Instructions
A1: Data Analyst weekly test 1
A2: Level: Easy to Intermediate | Time: 90 minutes | Total marks: 60
A4: How this exam works
A5: Part A has 7 Excel questions (35 marks). Part B has 5 SQL questions (25 marks). Every question is worth 5 marks.
A6: The Excel questions use the Sales_Data and Employee_Master sheets in this file. Do your Excel work directly on those sheets, or copy them into a fresh workbook.
A7: The SQL questions use the customers and orders tables shown on the SQL_Tables sheet. Write your queries in any SQL editor (MySQL, PostgreSQL or SQL Server all work, small syntax differences are fine).
A8: Questions marked Theory need a short written answer. Questions marked Practical need a formula, a result or a query. Many questions have both.

Sheet Question Paper
A1: Q No. | B1: Part | C1: Topic | D1: Type | E1: Difficulty | F1: Question | G1: Marks
A2: 1 | B2: A: Excel | C2: VLOOKUP | D2: Practical | E2: Easy | F2: On Sales_Data, column J is empty. Use VLOOKUP to bring in each salesperson's name from Employee_Master using EmpID, and fill it down for all 30 orders. (a) Write the formula for J2. (b) Why do we pass FALSE (or 0) as the last argument? (c) What does VLOOKUP return if the EmpID is not in the master list, and how would you show "Not Found" instead? | G2: 5
A3: 2 | B3: A: Excel | C3: INDEX MATCH | D3: Practical + Theory | E3: Intermediate | F3: Using INDEX and MATCH on Employee_Master: (a) Find the EmpID of Neha Verma. (Note that EmpID sits to the left of Name.) (b) Find the monthly salary of employee E105. (c) Give two reasons INDEX MATCH is often preferred over VLOOKUP. | G3: 5
A4: 3 | B4: A: Excel | C4: Sorting and Filtering | D4: Practical | E4: Easy | F4: On Sales_Data, apply a filter so that only orders from the South region with Qty of 5 or more are visible. (a) How many orders are left? (b) Sort the filtered rows by Revenue, largest first. Which OrderID is on top? (c) What is the difference between sorting and filtering? Does either one delete data? | G4: 5
A5: 4 | B5: A: Excel | C5: SUMIF and SUMIFS | D5: Practical | E5: Intermediate | F5: (a) Use SUMIF to get total Revenue for the North region. (b) Use SUMIFS to get total Revenue for orders in the West region AND the Electronics category. (c) Explain in one or two lines when you would pick SUMIFS over SUMIF. | G5: 5
A6: 5 | B6: A: Excel | C6: Arithmetic functions | D6: Practical | E6: Easy | F6: Using only the Revenue column, write formulas for: (a) Total revenue (b) Average order value, rounded to 2 decimals (c) Highest and lowest single-order revenue (d) Number of orders Also state which function would you use to count only the orders where Qty is greater than 5. | G6: 5
A7: 6 | B7: A: Excel | C7: Macros | D7: Theory | E7: Easy | F7: (a) What is a macro in Excel and what language does it record in? (b) Describe the steps to record a macro that formats a header row (bold, blue fill, centered). (c) Which file format must you save in to keep the macro, and why do some companies block macro files? | G7: 5
A8: 7 | B8: A: Excel | C8: Pivot Tables | D8: Practical | E8: Intermediate | F8: Build a pivot table from Sales_Data with Category in rows, Region in columns and Sum of Revenue in values. (a) Which Category earns the most overall? (b) Which Region earns the least overall? (c) You add 5 new rows under the data. The pivot does not change. What do you do? | G8: 5
A9: 8 | B9: B: SQL | C9: Data Cleaning | D9: Practical | E9: Intermediate | F9: Using the customers table: (a) Write a SELECT that returns full_name and city with extra spaces removed, city in upper case, and any NULL email shown as 'not provided'. (b) Write a query to find duplicate customers by email (ignore NULLs and ignore upper/lower case). (c) Name one other common data cleaning step an analyst does before reporting. | G9: 5
A10: 9 | B10: B: SQL | C10: DDL commands | D10: Practical + Theory | E10: Easy | F10: (a) Write a CREATE TABLE statement for products with: product_id (integer, primary key), product_name (up to 50 characters, cannot be empty), price (decimal with 2 places) and stock (integer, default 0). (b) Add a new column called category to it using ALTER TABLE. (c) Explain the difference between DELETE, TRUNCATE and DROP. | G10: 5
A11: 10 | B11: B: SQL | C11: DML commands | D11: Practical | E11: Easy | F11: On the orders table: (a) Insert a new order: order_id 107, customer_id 6, date 2026-03-25, amount 2200, status 'Pending'. (b) Update order 106 so its status becomes 'Delivered'. (c) Delete all orders with status 'Cancelled'. (d) What can go wrong if you run an UPDATE or DELETE without a WHERE clause? | G11: 5
A12: 11 | B12: B: SQL | C12: Clauses (WHERE, GROUP BY, HAVING, ORDER BY) | D12: Practical + Theory | E12: Intermediate | F12: On the original orders table, write one query that shows each customer_id with the total amount of their Delivered orders, keeps only customers whose total is above 2000, and lists the highest total first. Then explain the difference between WHERE and HAVING in two lines. | G12: 5
A13: 12 | B13: B: SQL | C13: Joins | D13: Practical + Theory | E13: Intermediate | F13: (a) Write a query that lists every customer with the number of orders they placed. Customers with no orders must still appear, with a count of 0. (b) How many rows would an INNER JOIN between customers and orders return, and which customers would be missing? (c) In plain words, what is the difference between INNER JOIN and LEFT JOIN? | G13: 5
F14: Total | G14: =SUM(G2:G13) -> 60
F15: Part A (Excel) subtotal | G15: =SUM(G2:G8) -> 35
F16: Part B (SQL) subtotal | G16: =SUM(G9:G13) -> 25

Sheet Employee_Master
A1: EmpID | B1: Name | C1: Team | D1: City | E1: Monthly Salary
A2: E101 | B2: Aarav Kapoor | C2: Sales | D2: Mumbai | E2: 42000
A3: E102 | B3: Neha Verma | C3: Sales | D3: Delhi | E3: 45000
A4: E103 | B4: Rohan Iyer | C4: Support | D4: Chennai | E4: 38000
A5: E104 | B5: Isha Gupta | C5: Sales | D5: Pune | E5: 41000
A6: E105 | B6: Vikram Singh | C6: Sales | D6: Jaipur | E6: 47000
A7: E106 | B7: Meera Joshi | C7: Marketing | D7: Mumbai | E7: 44000
A8: E107 | B8: Sanjay Rao | C8: Sales | D8: Hyderabad | E8: 43000
A9: E108 | B9: Pooja Desai | C9: Support | D9: Pune | E9: 36000

Sheet Sales_Data
A1: OrderID | B1: OrderDate | C1: EmpID | D1: Region | E1: Product | F1: Category | G1: Qty | H1: UnitPrice | I1: Revenue | J1: SalespersonName (fill for Q1)
A2: ORD1001 | B2: 46026 | C2: E102 | D2: West | E2: Notebook Pack | F2: Stationery | G2: 11 | H2: 300 | I2: =G2*H2 -> 3300
A3: ORD1002 | B3: 46029 | C3: E106 | D3: South | E3: Laptop | F3: Electronics | G3: 1 | H3: 55000 | I3: =G3*H3 -> 55000
A4: ORD1003 | B4: 46031 | C4: E101 | D4: North | E4: Desk | F4: Furniture | G4: 1 | H4: 9000 | I4: =G4*H4 -> 9000
A5: ORD1004 | B5: 46036 | C5: E101 | D5: North | E5: Office Chair | F5: Furniture | G5: 3 | H5: 6500 | I5: =G5*H5 -> 19500
A6: ORD1005 | B6: 46038 | C6: E107 | D6: South | E6: Laptop | F6: Electronics | G6: 3 | H6: 55000 | I6: =G6*H6 -> 165000
A7: ORD1006 | B7: 46040 | C7: E107 | D7: West | E7: Laptop | F7: Electronics | G7: 3 | H7: 55000 | I7: =G7*H7 -> 165000
A8: ORD1007 | B8: 46043 | C8: E101 | D8: East | E8: Headphones | F8: Electronics | G8: 5 | H8: 2500 | I8: =G8*H8 -> 12500
A9: ORD1008 | B9: 46046 | C9: E105 | D9: North | E9: Pen Set | F9: Stationery | G9: 3 | H9: 450 | I9: =G9*H9 -> 1350
A10: ORD1009 | B10: 46050 | C10: E101 | D10: North | E10: Notebook Pack | F10: Stationery | G10: 11 | H10: 300 | I10: =G10*H10 -> 3300
A11: ORD1010 | B11: 46052 | C11: E101 | D11: West | E11: Desk | F11: Furniture | G11: 3 | H11: 9000 | I11: =G11*H11 -> 27000
A12: ORD1011 | B12: 46057 | C12: E105 | D12: South | E12: Pen Set | F12: Stationery | G12: 6 | H12: 450 | I12: =G12*H12 -> 2700
A13: ORD1012 | B13: 46058 | C13: E103 | D13: North | E13: Office Chair | F13: Furniture | G13: 2 | H13: 6500 | I13: =G13*H13 -> 13000
... A31: ORD1030 | B31: 46114 | C31: E101 | D31: South | E31: Pen Set | F31: Stationery | G31: 11 | H31: 450 | I31: =G31*H31 -> 4950

Sheet SQL_Tables
A1: Table 1: customers (the data is messy on purpose)
A2: customer_id | B2: full_name | C2: email | D2: city | E2: phone | F2: signup_date
A3: 1 | B3: Rahul Sharma | C3: RAHUL@MAIL.COM | D3: mumbai | E3: 9876543210 | F3: 2025-11-02
A4: 2 | B4: Priya Nair | C4: priya@mail.com | D4: Pune | E4: NULL | F4: 2025-11-15
A5: 3 | B5: AMIT SHAH | C5: amit@mail.com | D5: delhi | E5: 9123456780 | F5: 2025-12-01
A6: 4 | B6: Priya Nair | C6: priya@mail.com | D6: Pune | E6: 9988776655 | F6: 2025-12-20
A7: 5 | B7: Sneha Rao | C7: NULL | D7: Chennai | E7: 9000011111 | F7: 2026-01-04
A8: 6 | B8: Karan Mehta | C8: karan@mail.com | D8: Mumbai | E8: 9345678901 | F8: 2026-01-18
A11: Table 2: orders
A12: order_id | B12: customer_id | C12: order_date | D12: amount | E12: status
A13: 101 | B13: 1 | C13: 2026-01-05 | D13: 2500 | E13: Delivered
A14: 102 | B14: 3 | C14: 2026-01-09 | D14: 1200 | E14: Delivered
A15: 103 | B15: 1 | C15: 2026-02-11 | D15: 3100 | E15: Cancelled
A16: 104 | B16: 2 | C16: 2026-02-15 | D16: 800 | E16: Delivered
A17: 105 | B17: 5 | C17: 2026-03-02 | D17: 4500 | E17: Delivered
A18: 106 | B18: 3 | C18: 2026-03-20 | D18: 1900 | E18: Pending
A20: Note: stray spaces in full_name and city are real, so TRIM matters. NULL means the cell is empty in the database.

Sheet marks awarding scheme 
A1: How to award marks
A2: (a) 2 marks, correct range lock and column index. (b) 1.5 marks. (c) 1.5 marks.
A3: (a) 1.5 marks. (b) 1.5 marks. (c) 2 marks, one for each valid reason.
A4: (a) 1.5 marks. (b) 1.5 marks. (c) 2 marks.
A5: (a) 1.5 marks. (b) 2 marks. (c) 1.5 marks. Deduct half a mark if the argument order is wrong.
A6: 1 mark each for (a) to (d), 1 mark for COUNTIF.
A7: (a) 1.5 marks. (b) 2 marks for correct steps in order. (c) 1.5 marks.
A8: (a) 1.5 marks. (b) 1.5 marks. (c) 2 marks, one for Refresh and one for source range or Table.
A9: (a) 2 marks (TRIM, UPPER and COALESCE each count). (b) 2 marks. (c) 1 mark.
A10: (a) 2 marks, 0.5 each for PK, NOT NULL, DECIMAL and DEFAULT. (b) 1 mark. (c) 2 marks.
A11: (a) 1.5 marks. (b) 1.5 marks. (c) 1 mark. (d) 1 mark.
A12: Query 3.5 marks (WHERE, GROUP BY, HAVING, ORDER BY about 0.75 each plus SUM). Explanation 1.5 marks.
A13: (a) 2 marks (LEFT JOIN 1, COUNT on o.order_id 0.5, GROUP BY 0.5). (b) 1.5 marks. (c) 1.5 marks.
A17: East | B17: West | C17: Grand Total
A18: =SUMIFS(Sales_Data!$I$2:$I$31,Sales_Data!$F$2:$F$31,#REF!,Sales_Data!$D$2:$D$31,A$17) -> 0 | B18: =SUMIFS(Sales_Data!$I$2:$I$31,Sales_Data!$F$2:$F$31,#REF!,Sales_Data!$D$2:$D$31,B$17) -> 0 | C18: =SUM(A18:B18) -> 0
A19: =SUMIFS(Sales_Data!$I$2:$I$31,Sales_Data!$F$2:$F$31,#REF!,Sales_Data!$D$2:$D$31,A$17) -> 0 | B19: =SUMIFS(Sales_Data!$I$2:$I$31,Sales_Data!$F$2:$F$31,#REF!,Sales_Data!$D$2:$D$31,B$17) -> 0 | C19: =SUM(A19:B19) -> 0
A20: =SUMIFS(Sales_Data!$I$2:$I$31,Sales_Data!$F$2:$F$31,#REF!,Sales_Data!$D$2:$D$31,A$17) -> 0 | B20: =SUMIFS(Sales_Data!$I$2:$I$31,Sales_Data!$F$2:$F$31,#REF!,Sales_Data!$D$2:$D$31,B$17) -> 0 | C20: =SUM(A20:B20) -> 0
A21: =SUM(A18:A20) -> 0 | B21: =SUM(B18:B20) -> 0 | C21: =SUM(C18:C20) -> 0
